pyomexmeta/__init__.py
pyomexmeta/api_tests.py
pyomexmeta/libOmexMetaCAPI.so.1.2.14
pyomexmeta/pyomexmeta.py
pyomexmeta/pyomexmeta_api.py
pyomexmeta/pyomexmeta_tests.py
pyomexmeta/test_strings.py
pyomexmeta-1.2.14.1.dist-info/LICENCE.txt
pyomexmeta-1.2.14.1.dist-info/METADATA
pyomexmeta-1.2.14.1.dist-info/WHEEL
pyomexmeta-1.2.14.1.dist-info/top_level.txt
pyomexmeta-1.2.14.1.dist-info/RECORD
