Metadata-Version: 2.1
Name: pyomexmeta
Version: 1.2.14.1
Home-page: https://github.com/sys-bio/libomexmeta
Author: Ciaran Welsh
Author-email: cw00137@gmail.com
License: MIT
Keywords: annotation,rdf
Platform: Windows
Platform: Linux
Platform: Unix
Platform: Mac OS-X
Classifier: Development Status :: 3 - Alpha
Classifier: Intended Audience :: Science/Research
Classifier: Intended Audience :: Developers
Classifier: License :: OSI Approved :: Apache Software License
Classifier: Programming Language :: C
Classifier: Programming Language :: C++
Classifier: Programming Language :: Python
Classifier: Programming Language :: Python :: 3.7
Classifier: Programming Language :: Python :: 3.8
Classifier: Programming Language :: Python :: 3.9
Classifier: Programming Language :: Python :: 3 :: Only
Classifier: Programming Language :: Python :: Implementation :: CPython
Classifier: Topic :: Software Development
Classifier: Topic :: Scientific/Engineering
Classifier: Operating System :: Microsoft :: Windows
Classifier: Operating System :: MacOS
Classifier: Operating System :: POSIX
Classifier: Operating System :: Unix
License-File: LICENCE.txt
Requires-Dist: graphviz (>=0.15)
Requires-Dist: pydot (>=1.4.1)
Requires-Dist: pywin32 ; sys_platform == "win32"
